dv_api_metrics/__init__.py
dv_api_metrics/apiquery.py
dv_api_metrics/collection_dataset_citations_2025_12_18_11_13.tsv
dv_api_metrics/collection_dataset_citations_2025_12_18_11_21.tsv
dv_api_metrics/collection_datasets_per_subject_count_2025_12_18_11_30.tsv
dv_api_metrics/collection_datasets_per_subject_count_2025_12_18_12_09.tsv
dv_api_metrics/report.py
dv_api_metrics/scripts/__init__.py
dv_api_metrics/scripts/collection_dataset_citations_2025_12_21_18_36.tsv
dv_api_metrics/scripts/collection_inventory_2025_12_21_18_39.tsv
dv_api_metrics/scripts/collection_inventory_2025_12_21_18_42.tsv
dv_api_metrics/scripts/collection_inventory_2025_12_21_18_48.tsv
dv_api_metrics/scripts/collection_inventory_2025_12_22_09_22.tsv
dv_api_metrics/scripts/collection_inventory_2025_12_22_09_26.tsv
dv_api_metrics/scripts/collection_inventory_2025_12_22_09_32.tsv
dv_api_metrics/scripts/collection_inventory_2026_01_14_12_56.tsv
dv_api_metrics/scripts/collection_inventory_2026_01_14_13_09.tsv
dv_api_metrics/scripts/collection_inventory_2026_01_14_13_41.tsv
dv_api_metrics/scripts/collection_inventory_2026_01_14_14_01.tsv
dv_api_metrics/scripts/collection_inventory_2026_01_14_14_01_unique_counts.txt
dv_api_metrics/scripts/collection_inventory_2026_01_15_07_53.tsv
dv_api_metrics/scripts/collection_inventory_2026_01_15_07_53_unique_counts.txt
dv_api_metrics/scripts/collection_inventory_2026_01_15_07_57.tsv
dv_api_metrics/scripts/collection_inventory_2026_01_15_07_57_unique_counts.txt
dv_api_metrics/scripts/collection_inventory_2026_01_15_07_58.tsv
dv_api_metrics/scripts/collection_inventory_2026_01_15_07_58_unique_counts.txt
dv_api_metrics/scripts/collection_inventory_2026_01_15_08_00.tsv
dv_api_metrics/scripts/collection_inventory_2026_01_15_08_00_unique_counts.txt
dv_api_metrics/scripts/collection_inventory_2026_01_15_10_21.tsv
dv_api_metrics/scripts/collection_inventory_2026_01_15_10_21_unique_counts.txt
dv_api_metrics/scripts/collection_inventory_2026_01_15_10_26.tsv
dv_api_metrics-0.2.9.dist-info/METADATA
dv_api_metrics-0.2.9.dist-info/WHEEL
dv_api_metrics-0.2.9.dist-info/entry_points.txt
dv_api_metrics-0.2.9.dist-info/licenses/LICENSE
dv_api_metrics-0.2.9.dist-info/RECORD
